vphack
