Metadata-Version: 2.1
Name: vphack
Version: 0.0.3
Summary: A Tools Viper Hacker @onehack
Home-page: https://github.com/NRTnarathip/vphackez.git
Author: Viper Hacker
Author-email: viperhackerth@gmail.com
License: License.txt
Platform: UNKNOWN
Classifier: Development Status :: 3 - Alpha
Classifier: Intended Audience :: Developers
Classifier: Topic :: Software Development :: Build Tools
Classifier: Programming Language :: Python :: 3
Classifier: License :: OSI Approved :: MIT License
